gen/PSLexer.py
gen/PSListener.py
gen/PSParser.py
gen/__init__.py
latex2sympy_custom4/__init__.py
latex2sympy_custom4/process_latex.py
latex2sympy_custom4-0.0.4.dist-info/LICENSE
latex2sympy_custom4-0.0.4.dist-info/METADATA
latex2sympy_custom4-0.0.4.dist-info/WHEEL
latex2sympy_custom4-0.0.4.dist-info/top_level.txt
latex2sympy_custom4-0.0.4.dist-info/RECORD
