Metadata-Version: 2.1
Name: latex2sympy-custom4
Version: 0.0.4
Summary: A simple rearrangement and packaged version of augustt198's latex2sympy using ANTLR
Home-page: UNKNOWN
Author: presidentkevvol
Author-email: helsinkiwhite@gmail.com
License: UNKNOWN
Platform: UNKNOWN
Classifier: Programming Language :: Python :: 3
Classifier: License :: OSI Approved :: MIT License
Classifier: Operating System :: OS Independent
Requires-Python: >=3.6
